montyhall/__init__.py
montyhall/monty.py
montyhall-0.1.0.dist-info/LICENSE
montyhall-0.1.0.dist-info/METADATA
montyhall-0.1.0.dist-info/WHEEL
montyhall-0.1.0.dist-info/top_level.txt
montyhall-0.1.0.dist-info/RECORD
