Metadata-Version: 2.1
Name: montyhall
Version: 0.1.0
Summary: This is a package to run the Monty Hall experiment
Home-page: https://github.com/jviegas6/montyHall
Author: Jose Viegas
Author-email: jviegas6@gmail.com
License: Apache License 2.0
Platform: UNKNOWN
Requires-Python: >=3.6
Requires-Dist: pandas (>=1.0.0)
